easy_exec/__init__.py
easy_exec/easy_exec.py
easy_exec-0.0.1.dist-info/LICENSE
easy_exec-0.0.1.dist-info/METADATA
easy_exec-0.0.1.dist-info/WHEEL
easy_exec-0.0.1.dist-info/top_level.txt
easy_exec-0.0.1.dist-info/RECORD
